[
    {
        "matchID": 72370,
        "matchDateTime": "2025-01-17T20:30:00",
        "timeZoneID": "W. Europe Standard Time",
        "leagueId": 4741,
        "leagueName": "1. Fußball-Bundesliga 2024/2025",
        "leagueSeason": 2024,
        "leagueShortcut": "bl1",
        "matchDateTimeUTC": "2025-01-17T19:30:00Z",
        "group": {
            "groupName": "18. Spieltag",
            "groupOrderID": 18,
            "groupID": 45134
        },
        "team1": {
            "teamId": 91,
            "teamName": "Eintracht Frankfurt",
            "shortName": "Frankfurt",
            "teamIconUrl": "https://i.imgur.com/X8NFkOb.png",
            "teamGroupName": null
        },
        "team2": {
            "teamId": 7,
            "teamName": "Borussia Dortmund",
            "shortName": "Dortmund",
            "teamIconUrl": "https://upload.wikimedia.org/wikipedia/commons/thumb/6/67/Borussia_Dortmund_logo.svg/560px-Borussia_Dortmund_logo.svg.png",
            "teamGroupName": null
        },
        "lastUpdateDateTime": "2025-01-17T22:24:46.84",
        "matchIsFinished": true,
        "matchResults": [
            {
                "resultID": 113977,
                "resultName": "Halbzeitergebnis",
                "pointsTeam1": 1,
                "pointsTeam2": 0,
                "resultOrderID": 1,
                "resultTypeID": 1,
                "resultDescription": "Ergebnis nach Ende der ersten Halbzeit"
            },
            {
                "resultID": 113978,
                "resultName": "Endergebnis",
                "pointsTeam1": 2,
                "pointsTeam2": 0,
                "resultOrderID": 2,
                "resultTypeID": 2,
                "resultDescription": "Ergebnis nach Ende der offiziellen Spielzeit"
            }
        ],
        "goals": [
            {
                "goalID": 122731,
                "scoreTeam1": 1,
                "scoreTeam2": 0,
                "matchMinute": 18,
                "goalGetterID": 23168,
                "goalGetterName": "Hugo Ekitiké",
                "isPenalty": false,
                "isOwnGoal": false,
                "isOvertime": false,
                "comment": null
            },
            {
                "goalID": 122732,
                "scoreTeam1": 2,
                "scoreTeam2": 0,
                "matchMinute": 92,
                "goalGetterID": 23215,
                "goalGetterName": "Oscar Höjlund",
                "isPenalty": false,
                "isOwnGoal": false,
                "isOvertime": false,
                "comment": null
            }
        ],
        "location": null,
        "numberOfViewers": null
    },
    {
        "matchID": 72368,
        "matchDateTime": "2025-01-18T15:30:00",
        "timeZoneID": "W. Europe Standard Time",
        "leagueId": 4741,
        "leagueName": "1. Fußball-Bundesliga 2024/2025",
        "leagueSeason": 2024,
        "leagueShortcut": "bl1",
        "matchDateTimeUTC": "2025-01-18T14:30:00Z",
        "group": {
            "groupName": "18. Spieltag",
            "groupOrderID": 18,
            "groupID": 45134
        },
        "team1": {
            "teamId": 16,
            "teamName": "VfB Stuttgart",
            "shortName": "Stuttgart",
            "teamIconUrl": "https://i.imgur.com/v0tkpNx.png",
            "teamGroupName": null
        },
        "team2": {
            "teamId": 112,
            "teamName": "SC Freiburg",
            "shortName": "Freiburg",
            "teamIconUrl": "https://i.imgur.com/r3mvi0h.png",
            "teamGroupName": null
        },
        "lastUpdateDateTime": "2025-01-18T17:27:12.25",
        "matchIsFinished": true,
        "matchResults": [
            {
                "resultID": 113981,
                "resultName": "Halbzeitergebnis",
                "pointsTeam1": 3,
                "pointsTeam2": 0,
                "resultOrderID": 1,
                "resultTypeID": 1,
                "resultDescription": "Ergebnis nach Ende der ersten Halbzeit"
            },
            {
                "resultID": 113982,
                "resultName": "Endergebnis",
                "pointsTeam1": 4,
                "pointsTeam2": 0,
                "resultOrderID": 2,
                "resultTypeID": 2,
                "resultDescription": "Ergebnis nach Ende der offiziellen Spielzeit"
            }
        ],
        "goals": [
            {
                "goalID": 122736,
                "scoreTeam1": 1,
                "scoreTeam2": 0,
                "matchMinute": 2,
                "goalGetterID": 23216,
                "goalGetterName": "Anthony Rouault",
                "isPenalty": false,
                "isOwnGoal": false,
                "isOvertime": false,
                "comment": null
            },
            {
                "goalID": 122739,
                "scoreTeam1": 2,
                "scoreTeam2": 0,
                "matchMinute": 17,
                "goalGetterID": 23217,
                "goalGetterName": "Ermedin Demirovic",
                "isPenalty": false,
                "isOwnGoal": false,
                "isOvertime": false,
                "comment": null
            },
            {
                "goalID": 122763,
                "scoreTeam1": 4,
                "scoreTeam2": 0,
                "matchMinute": 80,
                "goalGetterID": 16686,
                "goalGetterName": "Undav",
                "isPenalty": false,
                "isOwnGoal": false,
                "isOvertime": false,
                "comment": null
            },
            {
                "goalID": 122755,
                "scoreTeam1": 3,
                "scoreTeam2": 0,
                "matchMinute": 50,
                "goalGetterID": 22473,
                "goalGetterName": "N. Woltemade",
                "isPenalty": false,
                "isOwnGoal": false,
                "isOvertime": true,
                "comment": null
            }
        ],
        "location": null,
        "numberOfViewers": null
    },
    {
        "matchID": 72369,
        "matchDateTime": "2025-01-18T15:30:00",
        "timeZoneID": "W. Europe Standard Time",
        "leagueId": 4741,
        "leagueName": "1. Fußball-Bundesliga 2024/2025",
        "leagueSeason": 2024,
        "leagueShortcut": "bl1",
        "matchDateTimeUTC": "2025-01-18T14:30:00Z",
        "group": {
            "groupName": "18. Spieltag",
            "groupOrderID": 18,
            "groupID": 45134
        },
        "team1": {
            "teamId": 40,
            "teamName": "FC Bayern München",
            "shortName": "Bayern",
            "teamIconUrl": "https://upload.wikimedia.org/wikipedia/commons/1/1f/Logo_FC_Bayern_M%C3%BCnchen_%282002%E2%80%932017%29.svg",
            "teamGroupName": null
        },
        "team2": {
            "teamId": 131,
            "teamName": "VfL Wolfsburg",
            "shortName": "Wolfsburg",
            "teamIconUrl": "https://i.imgur.com/ucqKV4B.png",
            "teamGroupName": null
        },
        "lastUpdateDateTime": "2025-01-18T17:27:18.547",
        "matchIsFinished": true,
        "matchResults": [
            {
                "resultID": 113983,
                "resultName": "Halbzeitergebnis",
                "pointsTeam1": 2,
                "pointsTeam2": 1,
                "resultOrderID": 1,
                "resultTypeID": 1,
                "resultDescription": "Ergebnis nach Ende der ersten Halbzeit"
            },
            {
                "resultID": 113984,
                "resultName": "Endergebnis",
                "pointsTeam1": 3,
                "pointsTeam2": 2,
                "resultOrderID": 2,
                "resultTypeID": 2,
                "resultDescription": "Ergebnis nach Ende der offiziellen Spielzeit"
            }
        ],
        "goals": [
            {
                "goalID": 122752,
                "scoreTeam1": 2,
                "scoreTeam2": 1,
                "matchMinute": 39,
                "goalGetterID": 22945,
                "goalGetterName": "Michael Olise",
                "isPenalty": false,
                "isOwnGoal": false,
                "isOvertime": false,
                "comment": ""
            },
            {
                "goalID": 122743,
                "scoreTeam1": 1,
                "scoreTeam2": 1,
                "matchMinute": 24,
                "goalGetterID": 22976,
                "goalGetterName": "M. Amoura",
                "isPenalty": false,
                "isOwnGoal": false,
                "isOvertime": false,
                "comment": null
            },
            {
                "goalID": 122765,
                "scoreTeam1": 3,
                "scoreTeam2": 2,
                "matchMinute": 88,
                "goalGetterID": 22976,
                "goalGetterName": "M. Amoura",
                "isPenalty": false,
                "isOwnGoal": false,
                "isOvertime": false,
                "comment": null
            },
            {
                "goalID": 122740,
                "scoreTeam1": 1,
                "scoreTeam2": 0,
                "matchMinute": 20,
                "goalGetterID": 11373,
                "goalGetterName": "Leon Goretzka",
                "isPenalty": false,
                "isOwnGoal": false,
                "isOvertime": false,
                "comment": null
            },
            {
                "goalID": 122761,
                "scoreTeam1": 3,
                "scoreTeam2": 1,
                "matchMinute": 62,
                "goalGetterID": 11373,
                "goalGetterName": "Leon Goretzka",
                "isPenalty": false,
                "isOwnGoal": false,
                "isOvertime": false,
                "comment": ""
            }
        ],
        "location": null,
        "numberOfViewers": null
    },
    {
        "matchID": 72371,
        "matchDateTime": "2025-01-18T15:30:00",
        "timeZoneID": "W. Europe Standard Time",
        "leagueId": 4741,
        "leagueName": "1. Fußball-Bundesliga 2024/2025",
        "leagueSeason": 2024,
        "leagueShortcut": "bl1",
        "matchDateTimeUTC": "2025-01-18T14:30:00Z",
        "group": {
            "groupName": "18. Spieltag",
            "groupOrderID": 18,
            "groupID": 45134
        },
        "team1": {
            "teamId": 199,
            "teamName": "1. FC Heidenheim 1846",
            "shortName": "Heidenheim",
            "teamIconUrl": "https://upload.wikimedia.org/wikipedia/commons/thumb/9/9d/1._FC_Heidenheim_1846.svg/830px-1._FC_Heidenheim_1846.svg.png",
            "teamGroupName": null
        },
        "team2": {
            "teamId": 98,
            "teamName": "FC St. Pauli",
            "shortName": "St. Pauli",
            "teamIconUrl": "https://upload.wikimedia.org/wikipedia/de/b/b3/Fc_st_pauli_logo.svg",
            "teamGroupName": null
        },
        "lastUpdateDateTime": "2025-01-18T17:27:37.89",
        "matchIsFinished": true,
        "matchResults": [
            {
                "resultID": 113985,
                "resultName": "Halbzeitergebnis",
                "pointsTeam1": 0,
                "pointsTeam2": 1,
                "resultOrderID": 1,
                "resultTypeID": 1,
                "resultDescription": "Ergebnis nach Ende der ersten Halbzeit"
            },
            {
                "resultID": 113986,
                "resultName": "Endergebnis",
                "pointsTeam1": 0,
                "pointsTeam2": 2,
                "resultOrderID": 2,
                "resultTypeID": 2,
                "resultDescription": "Ergebnis nach Ende der offiziellen Spielzeit"
            }
        ],
        "goals": [
            {
                "goalID": 122742,
                "scoreTeam1": 0,
                "scoreTeam2": 1,
                "matchMinute": 25,
                "goalGetterID": 16947,
                "goalGetterName": "Johannes Eggestein",
                "isPenalty": false,
                "isOwnGoal": false,
                "isOvertime": false,
                "comment": null
            },
            {
                "goalID": 122766,
                "scoreTeam1": 0,
                "scoreTeam2": 2,
                "matchMinute": 92,
                "goalGetterID": 23156,
                "goalGetterName": "M. Guilavogui",
                "isPenalty": false,
                "isOwnGoal": false,
                "isOvertime": true,
                "comment": null
            }
        ],
        "location": null,
        "numberOfViewers": null
    },
    {
        "matchID": 72374,
        "matchDateTime": "2025-01-18T15:30:00",
        "timeZoneID": "W. Europe Standard Time",
        "leagueId": 4741,
        "leagueName": "1. Fußball-Bundesliga 2024/2025",
        "leagueSeason": 2024,
        "leagueShortcut": "bl1",
        "matchDateTimeUTC": "2025-01-18T14:30:00Z",
        "group": {
            "groupName": "18. Spieltag",
            "groupOrderID": 18,
            "groupID": 45134
        },
        "team1": {
            "teamId": 129,
            "teamName": "VfL Bochum",
            "shortName": "Bochum",
            "teamIconUrl": "https://i.imgur.com/5jy3Gfr.png",
            "teamGroupName": null
        },
        "team2": {
            "teamId": 1635,
            "teamName": "RB Leipzig",
            "shortName": "Leipzig",
            "teamIconUrl": "https://i.imgur.com/Rpwsjz1.png",
            "teamGroupName": null
        },
        "lastUpdateDateTime": "2025-01-18T17:27:03.827",
        "matchIsFinished": true,
        "matchResults": [
            {
                "resultID": 113987,
                "resultName": "Halbzeitergebnis",
                "pointsTeam1": 0,
                "pointsTeam2": 3,
                "resultOrderID": 1,
                "resultTypeID": 1,
                "resultDescription": "Ergebnis nach Ende der ersten Halbzeit"
            },
            {
                "resultID": 113988,
                "resultName": "Endergebnis",
                "pointsTeam1": 3,
                "pointsTeam2": 3,
                "resultOrderID": 2,
                "resultTypeID": 2,
                "resultDescription": "Ergebnis nach Ende der offiziellen Spielzeit"
            }
        ],
        "goals": [
            {
                "goalID": 122756,
                "scoreTeam1": 1,
                "scoreTeam2": 3,
                "matchMinute": 48,
                "goalGetterID": 22943,
                "goalGetterName": "Myron Boadu",
                "isPenalty": false,
                "isOwnGoal": false,
                "isOvertime": false,
                "comment": null
            },
            {
                "goalID": 122758,
                "scoreTeam1": 2,
                "scoreTeam2": 3,
                "matchMinute": 57,
                "goalGetterID": 22943,
                "goalGetterName": "Myron Boadu",
                "isPenalty": false,
                "isOwnGoal": false,
                "isOvertime": false,
                "comment": null
            },
            {
                "goalID": 122759,
                "scoreTeam1": 3,
                "scoreTeam2": 3,
                "matchMinute": 61,
                "goalGetterID": 22943,
                "goalGetterName": "Myron Boadu",
                "isPenalty": false,
                "isOwnGoal": false,
                "isOvertime": false,
                "comment": null
            },
            {
                "goalID": 122741,
                "scoreTeam1": 0,
                "scoreTeam2": 3,
                "matchMinute": 22,
                "goalGetterID": 17892,
                "goalGetterName": "Christoph Baumgartner",
                "isPenalty": false,
                "isOwnGoal": false,
                "isOvertime": false,
                "comment": null
            },
            {
                "goalID": 122737,
                "scoreTeam1": 0,
                "scoreTeam2": 1,
                "matchMinute": 10,
                "goalGetterID": 23131,
                "goalGetterName": "W. Orbán",
                "isPenalty": false,
                "isOwnGoal": false,
                "isOvertime": false,
                "comment": null
            },
            {
                "goalID": 122738,
                "scoreTeam1": 0,
                "scoreTeam2": 2,
                "matchMinute": 13,
                "goalGetterID": 22891,
                "goalGetterName": "A. Nusa",
                "isPenalty": false,
                "isOwnGoal": false,
                "isOvertime": false,
                "comment": null
            }
        ],
        "location": null,
        "numberOfViewers": null
    },
    {
        "matchID": 72375,
        "matchDateTime": "2025-01-18T15:30:00",
        "timeZoneID": "W. Europe Standard Time",
        "leagueId": 4741,
        "leagueName": "1. Fußball-Bundesliga 2024/2025",
        "leagueSeason": 2024,
        "leagueShortcut": "bl1",
        "matchDateTimeUTC": "2025-01-18T14:30:00Z",
        "group": {
            "groupName": "18. Spieltag",
            "groupOrderID": 18,
            "groupID": 45134
        },
        "team1": {
            "teamId": 104,
            "teamName": "Holstein Kiel",
            "shortName": "Kiel",
            "teamIconUrl": "https://upload.wikimedia.org/wikipedia/commons/thumb/3/30/Holstein_Kiel_Logo.svg/300px-Holstein_Kiel_Logo.svg.png",
            "teamGroupName": null
        },
        "team2": {
            "teamId": 175,
            "teamName": "TSG 1899 Hoffenheim",
            "shortName": "Hoffenheim",
            "teamIconUrl": "https://i.imgur.com/gF0PfEl.png",
            "teamGroupName": null
        },
        "lastUpdateDateTime": "2025-01-18T17:47:26.58",
        "matchIsFinished": true,
        "matchResults": [
            {
                "resultID": 113989,
                "resultName": "Halbzeitergebnis",
                "pointsTeam1": 0,
                "pointsTeam2": 2,
                "resultOrderID": 1,
                "resultTypeID": 1,
                "resultDescription": "Ergebnis nach Ende der ersten Halbzeit"
            },
            {
                "resultID": 113990,
                "resultName": "Endergebnis",
                "pointsTeam1": 1,
                "pointsTeam2": 3,
                "resultOrderID": 2,
                "resultTypeID": 2,
                "resultDescription": "Ergebnis nach Ende der offiziellen Spielzeit"
            }
        ],
        "goals": [
            {
                "goalID": 122744,
                "scoreTeam1": 0,
                "scoreTeam2": 1,
                "matchMinute": 26,
                "goalGetterID": 23151,
                "goalGetterName": "A. Hložek",
                "isPenalty": false,
                "isOwnGoal": false,
                "isOvertime": false,
                "comment": null
            },
            {
                "goalID": 122757,
                "scoreTeam1": 0,
                "scoreTeam2": 3,
                "matchMinute": 56,
                "goalGetterID": 23151,
                "goalGetterName": "A. Hložek",
                "isPenalty": false,
                "isOwnGoal": false,
                "isOvertime": false,
                "comment": null
            },
            {
                "goalID": 122753,
                "scoreTeam1": 0,
                "scoreTeam2": 2,
                "matchMinute": 46,
                "goalGetterID": 23218,
                "goalGetterName": "Andrej Kramaric",
                "isPenalty": false,
                "isOwnGoal": false,
                "isOvertime": true,
                "comment": null
            },
            {
                "goalID": 122762,
                "scoreTeam1": 1,
                "scoreTeam2": 3,
                "matchMinute": 84,
                "goalGetterID": 23219,
                "goalGetterName": "Andu Kelati",
                "isPenalty": false,
                "isOwnGoal": false,
                "isOvertime": false,
                "comment": null
            }
        ],
        "location": null,
        "numberOfViewers": null
    },
    {
        "matchID": 72367,
        "matchDateTime": "2025-01-18T18:30:00",
        "timeZoneID": "W. Europe Standard Time",
        "leagueId": 4741,
        "leagueName": "1. Fußball-Bundesliga 2024/2025",
        "leagueSeason": 2024,
        "leagueShortcut": "bl1",
        "matchDateTimeUTC": "2025-01-18T17:30:00Z",
        "group": {
            "groupName": "18. Spieltag",
            "groupOrderID": 18,
            "groupID": 45134
        },
        "team1": {
            "teamId": 6,
            "teamName": "Bayer Leverkusen",
            "shortName": "Leverkusen",
            "teamIconUrl": "https://www.bundesliga-reisefuehrer.de/sites/default/files/B04_Standard_Logo_RGB.png",
            "teamGroupName": null
        },
        "team2": {
            "teamId": 87,
            "teamName": "Borussia Mönchengladbach",
            "shortName": "Gladbach",
            "teamIconUrl": "https://i.imgur.com/KSIk0Eu.png",
            "teamGroupName": null
        },
        "lastUpdateDateTime": "2025-01-18T20:22:48.123",
        "matchIsFinished": true,
        "matchResults": [
            {
                "resultID": 113997,
                "resultName": "Halbzeitergebnis",
                "pointsTeam1": 1,
                "pointsTeam2": 0,
                "resultOrderID": 1,
                "resultTypeID": 1,
                "resultDescription": "Ergebnis nach Ende der ersten Halbzeit"
            },
            {
                "resultID": 113998,
                "resultName": "Endergebnis",
                "pointsTeam1": 3,
                "pointsTeam2": 1,
                "resultOrderID": 2,
                "resultTypeID": 2,
                "resultDescription": "Ergebnis nach Ende der offiziellen Spielzeit"
            }
        ],
        "goals": [
            {
                "goalID": 122770,
                "scoreTeam1": 3,
                "scoreTeam2": 1,
                "matchMinute": 91,
                "goalGetterID": 17785,
                "goalGetterName": "Tim Kleindienst",
                "isPenalty": false,
                "isOwnGoal": false,
                "isOvertime": true,
                "comment": null
            },
            {
                "goalID": 122769,
                "scoreTeam1": 3,
                "scoreTeam2": 0,
                "matchMinute": 74,
                "goalGetterID": 22743,
                "goalGetterName": "Patrik Schick",
                "isPenalty": false,
                "isOwnGoal": false,
                "isOvertime": false,
                "comment": null
            },
            {
                "goalID": 122767,
                "scoreTeam1": 1,
                "scoreTeam2": 0,
                "matchMinute": 32,
                "goalGetterID": 18298,
                "goalGetterName": "Florian Wirtz",
                "isPenalty": false,
                "isOwnGoal": false,
                "isOvertime": false,
                "comment": null
            },
            {
                "goalID": 122768,
                "scoreTeam1": 2,
                "scoreTeam2": 0,
                "matchMinute": 62,
                "goalGetterID": 18298,
                "goalGetterName": "Florian Wirtz",
                "isPenalty": true,
                "isOwnGoal": false,
                "isOvertime": false,
                "comment": null
            }
        ],
        "location": null,
        "numberOfViewers": null
    },
    {
        "matchID": 72373,
        "matchDateTime": "2025-01-19T15:30:00",
        "timeZoneID": "W. Europe Standard Time",
        "leagueId": 4741,
        "leagueName": "1. Fußball-Bundesliga 2024/2025",
        "leagueSeason": 2024,
        "leagueShortcut": "bl1",
        "matchDateTimeUTC": "2025-01-19T14:30:00Z",
        "group": {
            "groupName": "18. Spieltag",
            "groupOrderID": 18,
            "groupID": 45134
        },
        "team1": {
            "teamId": 80,
            "teamName": "1. FC Union Berlin",
            "shortName": "Union Berlin",
            "teamIconUrl": "https://assets.dfb.de/uploads/000/018/232/small_union-Berlin.jpg",
            "teamGroupName": null
        },
        "team2": {
            "teamId": 81,
            "teamName": "1. FSV Mainz 05",
            "shortName": "Mainz",
            "teamIconUrl": "https://upload.wikimedia.org/wikipedia/commons/thumb/9/9e/Logo_Mainz_05.svg/1200px-Logo_Mainz_05.svg.png",
            "teamGroupName": null
        },
        "lastUpdateDateTime": "2025-01-19T17:27:55.78",
        "matchIsFinished": true,
        "matchResults": [
            {
                "resultID": 114019,
                "resultName": "Halbzeitergebnis",
                "pointsTeam1": 2,
                "pointsTeam2": 1,
                "resultOrderID": 1,
                "resultTypeID": 1,
                "resultDescription": "Ergebnis nach Ende der ersten Halbzeit"
            },
            {
                "resultID": 114020,
                "resultName": "Endergebnis",
                "pointsTeam1": 2,
                "pointsTeam2": 1,
                "resultOrderID": 2,
                "resultTypeID": 2,
                "resultDescription": "Ergebnis nach Ende der offiziellen Spielzeit"
            }
        ],
        "goals": [
            {
                "goalID": 122805,
                "scoreTeam1": 1,
                "scoreTeam2": 1,
                "matchMinute": 4,
                "goalGetterID": 18410,
                "goalGetterName": "N. Amiri",
                "isPenalty": true,
                "isOwnGoal": false,
                "isOvertime": false,
                "comment": null
            },
            {
                "goalID": 122806,
                "scoreTeam1": 2,
                "scoreTeam2": 1,
                "matchMinute": 24,
                "goalGetterID": 17688,
                "goalGetterName": "Robert Skov",
                "isPenalty": true,
                "isOwnGoal": false,
                "isOvertime": false,
                "comment": null
            },
            {
                "goalID": 122804,
                "scoreTeam1": 1,
                "scoreTeam2": 0,
                "matchMinute": 2,
                "goalGetterID": 23137,
                "goalGetterName": "B. Hollerbach",
                "isPenalty": false,
                "isOwnGoal": false,
                "isOvertime": false,
                "comment": null
            }
        ],
        "location": null,
        "numberOfViewers": null
    },
    {
        "matchID": 72372,
        "matchDateTime": "2025-01-19T17:30:00",
        "timeZoneID": "W. Europe Standard Time",
        "leagueId": 4741,
        "leagueName": "1. Fußball-Bundesliga 2024/2025",
        "leagueSeason": 2024,
        "leagueShortcut": "bl1",
        "matchDateTimeUTC": "2025-01-19T16:30:00Z",
        "group": {
            "groupName": "18. Spieltag",
            "groupOrderID": 18,
            "groupID": 45134
        },
        "team1": {
            "teamId": 134,
            "teamName": "Werder Bremen",
            "shortName": "Bremen",
            "teamIconUrl": "https://upload.wikimedia.org/wikipedia/commons/thumb/b/be/SV-Werder-Bremen-Logo.svg/681px-SV-Werder-Bremen-Logo.svg.png",
            "teamGroupName": null
        },
        "team2": {
            "teamId": 95,
            "teamName": "FC Augsburg",
            "shortName": "Augsburg",
            "teamIconUrl": "https://i.imgur.com/sdE62e2.png",
            "teamGroupName": null
        },
        "lastUpdateDateTime": "2025-01-19T19:26:12.317",
        "matchIsFinished": true,
        "matchResults": [
            {
                "resultID": 114025,
                "resultName": "Halbzeitergebnis",
                "pointsTeam1": 0,
                "pointsTeam2": 2,
                "resultOrderID": 1,
                "resultTypeID": 1,
                "resultDescription": "Ergebnis nach Ende der ersten Halbzeit"
            },
            {
                "resultID": 114026,
                "resultName": "Endergebnis",
                "pointsTeam1": 0,
                "pointsTeam2": 2,
                "resultOrderID": 2,
                "resultTypeID": 2,
                "resultDescription": "Ergebnis nach Ende der offiziellen Spielzeit"
            }
        ],
        "goals": [
            {
                "goalID": 122812,
                "scoreTeam1": 0,
                "scoreTeam2": 1,
                "matchMinute": 5,
                "goalGetterID": 22921,
                "goalGetterName": "S. Essende",
                "isPenalty": false,
                "isOwnGoal": false,
                "isOvertime": false,
                "comment": null
            },
            {
                "goalID": 122814,
                "scoreTeam1": 0,
                "scoreTeam2": 2,
                "matchMinute": 46,
                "goalGetterID": 22921,
                "goalGetterName": "S. Essende",
                "isPenalty": false,
                "isOwnGoal": false,
                "isOvertime": true,
                "comment": null
            }
        ],
        "location": null,
        "numberOfViewers": null
    }
]